MANIFEST.in
README.rst
setup.py
pyload/__init__.py
pyload/script.py
pyload.egg-info/PKG-INFO
pyload.egg-info/SOURCES.txt
pyload.egg-info/dependency_links.txt
pyload.egg-info/entry_points.txt
pyload.egg-info/requires.txt
pyload.egg-info/top_level.txt
pyload/resources/__init__.py
pyload/resources/pyload
pyload/resources/python
pyload/resources/xlib.zip
pyload/resources/__pycache__/__init__.cpython-35.pyc