Metadata-Version: 1.1
Name: pyload
Version: 0.1
Summary: pyload is a tool to create static binary from python code
Home-page: https://github.com/ajdiaz/pyload
Author: Andrés J. Díaz
Author-email: ajdiaz@inactive.io
License: MIT
Platform: UNKNOWN
Classifier: Development Status :: 4 - Beta
Classifier: Intended Audience :: Developers
Classifier: Natural Language :: English
Classifier: License :: OSI Approved :: MIT License
Classifier: Programming Language :: Python :: 2.7
Classifier: Programming Language :: Python :: 3.5
Classifier: Operating System :: POSIX :: Linux
Classifier: Programming Language :: Python
Classifier: Programming Language :: C
